cadast/__init__.py
cadast/graph.py
cadast/model.py
cadast/utils.py
cadast-0.0.6.dist-info/METADATA
cadast-0.0.6.dist-info/WHEEL
cadast-0.0.6.dist-info/licenses/LICENCE
cadast-0.0.6.dist-info/RECORD
