Metadata-Version: 2.4
Name: cadast
Version: 0.0.6
Summary: A python implement of CadaST
Project-URL: Homepage, https://github.com/Khadaq2001/CadaST
Project-URL: Issues, https://github.com/Khadaq2001/CadaST/issues
Author-email: Xianhan Qin <q764579066@gmail.com>
License-File: LICENCE
Classifier: License :: OSI Approved :: MIT License
Classifier: Operating System :: OS Independent
Classifier: Programming Language :: Python :: 3
Requires-Python: >=3.10
Requires-Dist: anndata>=0.10.9
Requires-Dist: numpy>=1.23.5
Requires-Dist: scikit-learn>=1.5.2
Requires-Dist: scipy>=1.13.0
Requires-Dist: tqdm>=4.66.5
